Workbook

Sheet Executive Summary
A2: CORPORATE REAL ESTATE PORTFOLIO & WORKPLACE ANALYTICS
A3: Executive Management Overview & Portfolio Operating Synthesis | Reporting Date: 2026-09-30 | Currency: INR (₹)
B5: Total Properties | C5: Total Usable Area | D5: Total Seat Capacity | E5: Assigned Headcount | F5: Average Utilization
B6: =COUNTA('Property Register'!A5:A29) | C6: =SUM('Property Register'!I5:I29) | D6: =SUM('Property Register'!J5:J29) | E6: =SUM('Property Register'!K5:K29) | F6: =AVERAGE('Occupancy Analysis'!G5:G29)/100
B8: Capacity Pressure | C8: Annual Operating Cost | D8: Cost per Occupied Seat | E8: Leases Expiring <= 12M | F8: Data Quality Pass Rate
B9: =AVERAGE('Occupancy Analysis'!L5:L29)/100 | C9: =SUM('Cost Analysis'!G5:G29) | D9: =AVERAGE('Cost Analysis'!J5:J29) | E9: =COUNTIF('Lease Tracker'!J5:J29, "Expiring <= 6M") + COUNTIF('Lease Tracker'!J5:J29, "Expiring 6-12M") | F9: =(282584 - 'Data Quality'!B6)/282584
B12: Regional Portfolio Rollup
B13: Region | C13: Properties | D13: Usable Area (m²) | E13: Capacity Seats | F13: Assigned Headcount | G13: Desk Sharing | H13: Annual Cost (INR)
B14: India | C14: =COUNTIF('Property Register'!C5:C29, "India") | D14: =SUMIF('Property Register'!C5:C29, "India", 'Property Register'!I5:I29) | E14: =SUMIF('Property Register'!C5:C29, "India", 'Property Register'!J5:J29) | F14: =SUMIF('Property Register'!C5:C29, "India", 'Property Register'!K5:K29) | G14: =F14/E14 | H14: =SUMIF('Property Register'!C5:C29, "India", 'Cost Analysis'!G5:G29)
B15: Asia-Pacific | C15: =COUNTIF('Property Register'!C5:C29, "Asia-Pacific") | D15: =SUMIF('Property Register'!C5:C29, "Asia-Pacific", 'Property Register'!I5:I29) | E15: =SUMIF('Property Register'!C5:C29, "Asia-Pacific", 'Property Register'!J5:J29) | F15: =SUMIF('Property Register'!C5:C29, "Asia-Pacific", 'Property Register'!K5:K29) | G15: =F15/E15 | H15: =SUMIF('Property Register'!C5:C29, "Asia-Pacific", 'Cost Analysis'!G5:G29)
B16: Total Regional Portfolio | C16: =SUM(C14:C15) | D16: =SUM(D14:D15) | E16: =SUM(E14:E15) | F16: =SUM(F14:F15) | G16: =F16/E16 | H16: =SUM(H14:H15)
B19: Executive Analytical Observations
B20: 1. Mid-Week vs. Monthly Average: Portfolio average utilization of 59.4% masks acute mid-week demand (Wednesdays hit 74.2% average and 89.1% peak), requiring peak-smoothing policies rather than indiscriminate seat reductions.
B21: 2. Cost Concentration: Singapore and Sydney command premium operating expenditure (₹122.9 Cr combined), requiring rigorous seat productivity review prior to approaching lease decisions.
B22: 3. Near-Term Leases: 10 lease events occur within 12 months (₹105.8 Cr annual base rent exposure), led by Singapore Marina Bay (Feb 2027) and Mumbai Nariman Point (Mar 2027).
B23: 4. Data Governance Confidence: 100% of injected raw defects (44 items) remediated and validated in clean analytical data layer with 99.98% overall pass rate.

Sheet Property Register
A2: PROPERTY REGISTER & SPATIAL MASTER
A3: Physical asset inventory, usable and rentable floor area, capacity, and density ratios
A4: Property Code | B4: Property Name | C4: Region | D4: Country | E4: City | F4: Facility Type | G4: Ownership | H4: Rentable Area (m²) | I4: Usable Area (m²) | J4: Capacity (Seats) | K4: Assigned Headcount | L4: Workplace Density (m²/seat) | M4: Sharing Ratio | N4: Core Loss Factor %
A5: PROP-BOM-01 | B5: Nariman Point Business Centre | C5: India | D5: India | E5: Mumbai | F5: Regional Headquarters | G5: Leased | H5: 8200 | I5: 6800 | J5: 620 | K5: 820 | L5: =I5/J5 | M5: =K5/J5 | N5: =(H5-I5)/H5
A6: PROP-BOM-02 | B6: BKC Central Tower B | C6: India | D6: India | E6: Mumbai | F6: Regional Sales & Client Office | G6: Leased | H6: 4500 | I6: 3750 | J6: 340 | K6: 480 | L6: =I6/J6 | M6: =K6/J6 | N6: =(H6-I6)/H6
A7: PROP-BOM-03 | B7: Powai Horizon Office Park | C7: India | D7: India | E7: Mumbai | F7: Business Operations Center | G7: Leased | H7: 12500 | I7: 10600 | J7: 1250 | K7: 1450 | L7: =I7/J7 | M7: =K7/J7 | N7: =(H7-I7)/H7
A8: PROP-PNQ-01 | B8: Hinjawadi Tech Campus A | C8: India | D8: India | E8: Pune | F8: Technology & Engineering Campus | G8: Owned | H8: 18000 | I8: 15500 | J8: 1720 | K8: 2150 | L8: =I8/J8 | M8: =K8/J8 | N8: =(H8-I8)/H8
A9: PROP-PNQ-02 | B9: Magarpatta Enterprise Park | C9: India | D9: India | E9: Pune | F9: Business Operations Center | G9: Leased | H9: 9200 | I9: 7800 | J9: 950 | K9: 1050 | L9: =I9/J9 | M9: =K9/J9 | N9: =(H9-I9)/H9
A10: PROP-BLR-01 | B10: Whitefield Innovation Campus Tower 1 | C10: India | D10: India | E10: Bengaluru | F10: Technology & Engineering Campus | G10: Leased | H10: 21000 | I10: 17850 | J10: 1980 | K10: 2600 | L10: =I10/J10 | M10: =K10/J10 | N10: =(H10-I10)/H10
A11: PROP-BLR-02 | B11: Outer Ring Road Alpha Center | C11: India | D11: India | E11: Bengaluru | F11: Technology & Engineering Campus | G11: Leased | H11: 14000 | I11: 11900 | J11: 1320 | K11: 1700 | L11: =I11/J11 | M11: =K11/J11 | N11: =(H11-I11)/H11
A12: PROP-BLR-03 | B12: Electronic City Systems Hub | C12: India | D12: India | E12: Bengaluru | F12: Business Operations Center | G12: Owned | H12: 11000 | I12: 9350 | J12: 1100 | K12: 1250 | L12: =I12/J12 | M12: =K12/J12 | N12: =(H12-I12)/H12
A13: PROP-MAA-01 | B13: OMR Cyber Gateway | C13: India | D13: India | E13: Chennai | F13: Technology & Engineering Campus | G13: Leased | H13: 13500 | I13: 11475 | J13: 1280 | K13: 1500 | L13: =I13/J13 | M13: =K13/J13 | N13: =(H13-I13)/H13
A14: PROP-MAA-02 | B14: Guindy Industrial Square | C14: India | D14: India | E14: Chennai | F14: Business Operations Center | G14: Leased | H14: 7500 | I14: 6375 | J14: 750 | K14: 820 | L14: =I14/J14 | M14: =K14/J14 | N14: =(H14-I14)/H14
A15: PROP-HYD-01 | B15: HITEC City Cyber Horizon | C15: India | D15: India | E15: Hyderabad | F15: Technology & Engineering Campus | G15: Leased | H15: 16000 | I15: 13600 | J15: 1500 | K15: 1950 | L15: =I15/J15 | M15: =K15/J15 | N15: =(H15-I15)/H15
A16: PROP-HYD-02 | B16: Gachibowli Financial Hub | C16: India | D16: India | E16: Hyderabad | F16: Regional Sales & Client Office | G16: Leased | H16: 5200 | I16: 4420 | J16: 420 | K16: 520 | L16: =I16/J16 | M16: =K16/J16 | N16: =(H16-I16)/H16
... A29: PROP-PNQ-03 | B29: Kalyani Nagar Gateway | C29: India | D29: India | E29: Pune | F29: Regional Sales & Client Office | G29: Leased | H29: 3800 | I29: 3200 | J29: 310 | K29: 390 | L29: =I29/J29 | M29: =K29/J29 | N29: =(H29-I29)/H29
A30: Portfolio Total / Average | H30: =SUM(H5:H29) | I30: =SUM(I5:I29) | J30: =SUM(J5:J29) | K30: =SUM(K5:K29) | L30: =I30/J30 | M30: =K30/J30 | N30: =(H30-I30)/H30

Sheet Occupancy Analysis
A2: WORKPLACE UTILIZATION & OCCUPANCY PERFORMANCE
A3: Daily presence, average utilization, peak rates, and capacity pressure choke points
A4: Property Code | B4: Property Name | C4: City | D4: Capacity (Seats) | E4: Avg Daily Presence | F4: Vacant Seats | G4: Average Utilization % | H4: Peak Utilization % | I4: Peak-Average Spread | J4: Pressure Quadrant | K4: Days Under Pressure | L4: Capacity Pressure %
A5: PROP-BOM-01 | B5: Nariman Point Business Centre | C5: Mumbai | D5: 620 | E5: 359.62083 | F5: =D5-E5 | G5: 58.77 | H5: 78.89 | I5: =H5-G5 | J5: Consistently active | K5: 3988 | L5: 794.42
A6: PROP-BOM-02 | B6: BKC Central Tower B | C6: Mumbai | D6: 340 | E6: 150.1875 | F6: =D6-E6 | G6: 44.61 | H6: 64.79 | I6: =H6-G6 | J6: Underutilized | K6: 413 | L6: 82.27
A7: PROP-BOM-03 | B7: Powai Horizon Office Park | C7: Mumbai | D7: 1250 | E7: 893.825 | F7: =D7-E7 | G7: 72.92 | H7: 84.54 | I7: =H7-G7 | J7: Capacity-constrained | K7: 5505 | L7: 1096.61
A8: PROP-PNQ-01 | B8: Hinjawadi Tech Campus A | C8: Pune | D8: 1720 | E8: 1122.05 | F8: =D8-E8 | G8: 65.88 | H8: 83.3 | I8: =H8-G8 | J8: Capacity-constrained | K8: 7108 | L8: 1415.94
A9: PROP-PNQ-02 | B9: Magarpatta Enterprise Park | C9: Pune | D9: 950 | E9: 360.83333 | F9: =D9-E9 | G9: 38.52 | H9: 48.17 | I9: =H9-G9 | J9: Underutilized | K9: 1 | L9: 0.2
A10: PROP-BLR-01 | B10: Whitefield Innovation Campus Tower 1 | C10: Bengaluru | D10: 1980 | E10: 1462.0417 | F10: =D10-E10 | G10: 74.96 | H10: 88.74 | I10: =H10-G10 | J10: Capacity-constrained | K10: 9513 | L10: 1895.02
A11: PROP-BLR-02 | B11: Outer Ring Road Alpha Center | C11: Bengaluru | D11: 1320 | E11: 908.94167 | F11: =D11-E11 | G11: 69.89 | H11: 85.26 | I11: =H11-G11 | J11: Capacity-constrained | K11: 5574 | L11: 1110.36
A12: PROP-BLR-03 | B12: Electronic City Systems Hub | C12: Bengaluru | D12: 1100 | E12: 542.45833 | F12: =D12-E12 | G12: 49.61 | H12: 62.05 | I12: =H12-G12 | J12: Underutilized | K12: 152 | L12: 30.28
A13: PROP-MAA-01 | B13: OMR Cyber Gateway | C13: Chennai | D13: 1280 | E13: 792.075 | F13: =D13-E13 | G13: 62.8 | H13: 80.6 | I13: =H13-G13 | J13: Capacity-constrained | K13: 4972 | L13: 990.44
A14: PROP-MAA-02 | B14: Guindy Industrial Square | C14: Chennai | D14: 750 | E14: 315.70833 | F14: =D14-E14 | G14: 42.59 | H14: 52.06 | I14: =H14-G14 | J14: Underutilized | K14: 1 | L14: 0.2
A15: PROP-HYD-01 | B15: HITEC City Cyber Horizon | C15: Hyderabad | D15: 1500 | E15: 1058.725 | F15: =D15-E15 | G15: 70.91 | H15: 86.57 | I15: =H15-G15 | J15: Capacity-constrained | K15: 6769 | L15: 1348.41
A16: PROP-HYD-02 | B16: Gachibowli Financial Hub | C16: Hyderabad | D16: 420 | E16: 222.60833 | F16: =D16-E16 | G16: 53.73 | H16: 75.03 | I16: =H16-G16 | J16: Underutilized | K16: 1801 | L16: 358.76
... A29: PROP-PNQ-03 | B29: Kalyani Nagar Gateway | C29: Pune | D29: 310 | E29: 145.96667 | F29: =D29-E29 | G29: 47.59 | H29: 65.65 | I29: =H29-G29 | J29: Underutilized | K29: 246 | L29: 49
A30: Portfolio Summary | D30: =SUM(D5:D29) | E30: =SUM(E5:E29) | F30: =D30-E30 | G30: =(E30/D30)*100 | H30: =AVERAGE(H5:H29) | I30: =H30-G30 | K30: =SUM(K5:K29) | L30: =AVERAGE(L5:L29)

Sheet Cost Analysis
A2: OCCUPANCY COST & FINANCIAL EFFICIENCY
A3: Operating expenses, cost per usable area, cost per seat, and vacant seat penalty
A4: Property Code | B4: Property Name | C4: City | D4: Local Currency | E4: Annual Operating Cost (INR) | F4: Cost per Usable m² (INR) | G4: Cost per Available Seat (INR) | H4: Cost per Occupied Seat (INR) | I4: Utilization Cost Premium (INR) | J4: Inefficiency Multiplier %
A5: PROP-BOM-01 | B5: Nariman Point Business Centre | C5: Mumbai | D5: INR | E5: 2.6171304e+08 | F5: =E5/'Property Register'!I5 | G5: =E5/'Property Register'!J5 | H5: =E5/'Occupancy Analysis'!E5 | I5: =H5-G5 | J5: =I5/G5
A6: PROP-BOM-02 | B6: BKC Central Tower B | C6: Mumbai | D6: INR | E6: 1.5990873e+08 | F6: =E6/'Property Register'!I6 | G6: =E6/'Property Register'!J6 | H6: =E6/'Occupancy Analysis'!E6 | I6: =H6-G6 | J6: =I6/G6
A7: PROP-BOM-03 | B7: Powai Horizon Office Park | C7: Mumbai | D7: INR | E7: 2.4957259e+08 | F7: =E7/'Property Register'!I7 | G7: =E7/'Property Register'!J7 | H7: =E7/'Occupancy Analysis'!E7 | I7: =H7-G7 | J7: =I7/G7
A8: PROP-PNQ-01 | B8: Hinjawadi Tech Campus A | C8: Pune | D8: INR | E8: 84067305 | F8: =E8/'Property Register'!I8 | G8: =E8/'Property Register'!J8 | H8: =E8/'Occupancy Analysis'!E8 | I8: =H8-G8 | J8: =I8/G8
A9: PROP-PNQ-02 | B9: Magarpatta Enterprise Park | C9: Pune | D9: INR | E9: 1.1778968e+08 | F9: =E9/'Property Register'!I9 | G9: =E9/'Property Register'!J9 | H9: =E9/'Occupancy Analysis'!E9 | I9: =H9-G9 | J9: =I9/G9
A10: PROP-BLR-01 | B10: Whitefield Innovation Campus Tower 1 | C10: Bengaluru | D10: INR | E10: 3.4402685e+08 | F10: =E10/'Property Register'!I10 | G10: =E10/'Property Register'!J10 | H10: =E10/'Occupancy Analysis'!E10 | I10: =H10-G10 | J10: =I10/G10
A11: PROP-BLR-02 | B11: Outer Ring Road Alpha Center | C11: Bengaluru | D11: INR | E11: 2.4498812e+08 | F11: =E11/'Property Register'!I11 | G11: =E11/'Property Register'!J11 | H11: =E11/'Occupancy Analysis'!E11 | I11: =H11-G11 | J11: =I11/G11
A12: PROP-BLR-03 | B12: Electronic City Systems Hub | C12: Bengaluru | D12: INR | E12: 49337327 | F12: =E12/'Property Register'!I12 | G12: =E12/'Property Register'!J12 | H12: =E12/'Occupancy Analysis'!E12 | I12: =H12-G12 | J12: =I12/G12
A13: PROP-MAA-01 | B13: OMR Cyber Gateway | C13: Chennai | D13: INR | E13: 1.8859241e+08 | F13: =E13/'Property Register'!I13 | G13: =E13/'Property Register'!J13 | H13: =E13/'Occupancy Analysis'!E13 | I13: =H13-G13 | J13: =I13/G13
A14: PROP-MAA-02 | B14: Guindy Industrial Square | C14: Chennai | D14: INR | E14: 99251511 | F14: =E14/'Property Register'!I14 | G14: =E14/'Property Register'!J14 | H14: =E14/'Occupancy Analysis'!E14 | I14: =H14-G14 | J14: =I14/G14
A15: PROP-HYD-01 | B15: HITEC City Cyber Horizon | C15: Hyderabad | D15: INR | E15: 2.4388318e+08 | F15: =E15/'Property Register'!I15 | G15: =E15/'Property Register'!J15 | H15: =E15/'Occupancy Analysis'!E15 | I15: =H15-G15 | J15: =I15/G15
A16: PROP-HYD-02 | B16: Gachibowli Financial Hub | C16: Hyderabad | D16: INR | E16: 85360488 | F16: =E16/'Property Register'!I16 | G16: =E16/'Property Register'!J16 | H16: =E16/'Occupancy Analysis'!E16 | I16: =H16-G16 | J16: =I16/G16
... A29: PROP-PNQ-03 | B29: Kalyani Nagar Gateway | C29: Pune | D29: INR | E29: 50241566 | F29: =E29/'Property Register'!I29 | G29: =E29/'Property Register'!J29 | H29: =E29/'Occupancy Analysis'!E29 | I29: =H29-G29 | J29: =I29/G29
A30: Portfolio Summary | E30: =SUM(E5:E29) | F30: =E30/'Property Register'!I30 | G30: =E30/'Property Register'!J30 | H30: =E30/'Occupancy Analysis'!E30 | I30: =H30-G30 | J30: =I30/G30

Sheet Lease Tracker
A2: LEASE TRACKER & CRITICAL DECISION HORIZONS
A3: Commercial lease commitments, critical expiry horizons, and notice obligations relative to 2026-09-30
A4: Property Code | B4: Property Name | C4: City | D4: Ownership | E4: Lease Contract | F4: Lease Start Date | G4: Lease End Date | H4: Notice Period (Mos) | I4: Annual Rent (INR) | J4: Expiry Horizon Category | K4: Lease Status
A5: PROP-BOM-01 | B5: Nariman Point Business Centre | C5: Mumbai | D5: Leased | E5: LSE-BOM-01-2022 | F5: 2022-04-01 | G5: 2027-03-31 | H5: 6 | I5: 204000000 | J5: Expiring <= 6M | K5: Expiring Near-Term
A6: PROP-BOM-02 | B6: BKC Central Tower B | C6: Mumbai | D6: Leased | E6: LSE-BOM-02-2020 | F6: 2020-11-01 | G6: 2028-10-31 | H6: 6 | I6: 126000000 | J6: Horizon > 24M | K6: Active
A7: PROP-BOM-03 | B7: Powai Horizon Office Park | C7: Mumbai | D7: Leased | E7: LSE-BOM-03-2023 | F7: 2023-01-01 | G7: 2029-12-31 | H7: 6 | I7: 178000000 | J7: Horizon > 24M | K7: Active
A8: PROP-PNQ-01 | B8: Hinjawadi Tech Campus A | C8: Pune | D8: Owned | E8: LSE-PNQ-01-2016 | F8: 2016-01-01 | G8: N/A (Owned) | H8: 0 | I8: 0 | J8: Owned | K8: Active (Owned)
A9: PROP-PNQ-02 | B9: Magarpatta Enterprise Park | C9: Pune | D9: Leased | E9: LSE-PNQ-02-2021 | F9: 2021-06-01 | G9: 2027-05-31 | H9: 6 | I9: 74880000 | J9: Expiring 6-12M | K9: Active
A10: PROP-BLR-01 | B10: Whitefield Innovation Campus Tower 1 | C10: Bengaluru | D10: Leased | E10: LSE-BLR-01-2021 | F10: 2021-10-01 | G10: 2027-09-30 | H10: 6 | I10: 235620000 | J10: Expiring 6-12M | K10: Active
A11: PROP-BLR-02 | B11: Outer Ring Road Alpha Center | C11: Bengaluru | D11: Leased | E11: LSE-BLR-02-2021 | F11: 2021-03-01 | G11: 2028-02-29 | H11: 6 | I11: 171360000 | J11: Expiring 12-24M | K11: Active
A12: PROP-BLR-03 | B12: Electronic City Systems Hub | C12: Bengaluru | D12: Owned | E12: LSE-BLR-03-2015 | F12: 2015-01-01 | G12: N/A (Owned) | H12: 0 | I12: 0 | J12: Owned | K12: Active (Owned)
A13: PROP-MAA-01 | B13: OMR Cyber Gateway | C13: Chennai | D13: Leased | E13: LSE-MAA-01-2022 | F13: 2022-08-01 | G13: 2028-07-31 | H13: 6 | I13: 123930000 | J13: Expiring 12-24M | K13: Active
A14: PROP-MAA-02 | B14: Guindy Industrial Square | C14: Chennai | D14: Leased | E14: LSE-MAA-02-2021 | F14: 2021-04-01 | G14: 2027-03-31 | H14: 6 | I14: 65025000 | J14: Expiring <= 6M | K14: Expiring Near-Term
A15: PROP-HYD-01 | B15: HITEC City Cyber Horizon | C15: Hyderabad | D15: Leased | E15: LSE-HYD-01-2023 | F15: 2023-05-01 | G15: 2029-04-30 | H15: 6 | I15: 163200000 | J15: Horizon > 24M | K15: Active
A16: PROP-HYD-02 | B16: Gachibowli Financial Hub | C16: Hyderabad | D16: Leased | E16: LSE-HYD-02-2021 | F16: 2021-12-01 | G16: 2027-11-30 | H16: 6 | I16: 58344000 | J16: Expiring 12-24M | K16: Active
... A29: PROP-PNQ-03 | B29: Kalyani Nagar Gateway | C29: Pune | D29: Leased | E29: LSE-PNQ-03-2022 | F29: 2022-03-01 | G29: 2028-02-29 | H29: 6 | I29: 32640000 | J29: Expiring 12-24M | K29: Active
A30: Total Contractual Rent | I30: =SUM(I5:I29)

Sheet Data Quality
A2: DATA QUALITY CONTROLS & AUDIT LEDGER
A3: Audit manifest logging 100% of injected raw defects and verified clean remediations
A5: Total Ingestion Records | B5: 282584
A6: Detected Anomaly Count | B6: =COUNTA(A11:A54)
A7: Critical Defects | B7: =COUNTIF(E11:E54, "Critical")
A8: Remediation Pass Rate | B8: =(B5-B6)/B5
A10: Issue ID | B10: Table Name | C10: Record Identifier | D10: Issue Type | E10: Severity | F10: Expected Validation Rule | G10: Injected Raw Value | H10: Corrected Clean Value
A11: DQ-ISS-001 | B11: raw_properties | C11: PROP-BOM-01 | D11: DQ009 | E11: Medium | F11: City must not be null or blank | G11: nan | H11: Mumbai
A12: DQ-ISS-002 | B12: raw_properties | C12: PROP-BLR-02 | D12: DQ005 | E12: High | F12: City must map to valid country | G12: Australia | H12: India
A13: DQ-ISS-003 | B13: raw_properties | C13: PROP-PNQ-03 | D13: DQ005 | E13: Medium | F13: City name must be properly capitalized and trimmed | G13: PUNE | H13: Pune
A14: DQ-ISS-004 | B14: raw_properties | C14: PROP-MAA-02 | D14: DQ006 | E14: High | F14: Usable area cannot exceed rentable area | G14: 8500.0 | H14: 6375.0
A15: DQ-ISS-005 | B15: raw_properties | C15: PROP-BOM-02 | D15: DQ001 | E15: Critical | F15: Property code must be unique | G15: Duplicate Record Injected | H15: Single Unique Record
A16: DQ-ISS-006 | B16: raw_leases | C16: LSE-DEL-01-2021 | D16: DQ004 | E16: Critical | F16: Lease end date cannot precede lease start date | G16: Start: 2027-06-30, End: 2021-07-01 | H16: Start: 2021-07-01, End: 2027-06-30
A17: DQ-ISS-007 | B17: raw_leases | C17: LSE-KUL-02-2023 | D17: DQ004 | E17: Critical | F17: Lease end date cannot precede lease start date | G17: Start: 2028-12-31, End: 2023-01-01 | H17: Start: 2023-01-01, End: 2028-12-31
A18: DQ-ISS-008 | B18: raw_leases | C18: LSE-BKK-02-2023 | D18: DQ009 | E18: High | F18: Lease end date must not be null or empty | G18: nan | H18: 2029-03-31
A19: DQ-ISS-009 | B19: raw_property_costs | C19: COST-3045 | D19: DQ008 | E19: High | F19: Operating cost values cannot be negative | G19: -3825000.0 | H19: 3825000.0
A20: DQ-ISS-010 | B20: raw_property_costs | C20: COST-3120 | D20: DQ008 | E20: High | F20: Energy cost cannot be negative | G20: -740353.81 | H20: 740353.81
A21: DQ-ISS-011 | B21: raw_property_costs | C21: COST-3280 | D21: DQ008 | E21: High | F21: Facilities cost cannot be negative | G21: -625594.69 | H21: 625594.69
... A54: DQ-ISS-044 | B54: raw_room_utilization | C54: ROOM-98401 | D54: DQ011 | E54: Medium | F54: Attended bookings cannot exceed total scheduled bookings | G54: 10 | H54: 7

Sheet Project Tracker
A2: PROJECT COORDINATION & WORKSTREAM TRACKER
A3: End-to-end milestone monitoring across Data, Analytics, Dashboard, Reporting, and QA
A5: Total Tasks | B5: =COUNTA(B11:B32)
A6: Completed Tasks | B6: =COUNTIF(E11:E32, "Complete")
A7: In Progress | B7: =COUNTIF(E11:E32, "In Progress")
A8: Overall Progress % | B8: =AVERAGE(J11:J32)/100
A10: Workstream | B10: Task ID | C10: Task Description | D10: Owner | E10: Status | F10: Priority | G10: Start Date | H10: Due Date | I10: Dependency | J10: Progress % | K10: Notes | L10: Last Updated
A11: Data | B11: DAT-01 | C11: Inspect local environment and configure dependencies | D11: Lead Analyst | E11: Complete | F11: Critical | G11: 2026-09-15 | H11: 2026-09-16 | I11: nan | J11: 100 | K11: Verified Python 3.14 openpyxl duckdb reportlab pptx | L11: 2026-09-16
A12: Data | B12: DAT-02 | C12: Conduct commercial real estate domain and benchmark research | D12: Lead Analyst | E12: Complete | F12: High | G12: 2026-09-16 | H12: 2026-09-18 | I12: DAT-01 | J12: 100 | K12: Authored docs/research_notes.md covering 20 CRE topics | L12: 2026-09-18
A13: Data | B13: DAT-03 | C13: Define portfolio star schema and data dictionary | D13: Lead Analyst | E13: Complete | F13: Critical | G13: 2026-09-18 | H13: 2026-09-19 | I13: DAT-02 | J13: 100 | K13: Authored data and metric dictionaries with strict constraints | L13: 2026-09-19
A14: Data | B14: DAT-04 | C14: Build deterministic synthetic data generation engine | D14: Lead Analyst | E14: Complete | F14: Critical | G14: 2026-09-19 | H14: 2026-09-22 | I14: DAT-03 | J14: 100 | K14: Generated 25 properties 112 floors 809 spaces and 282k fact rows | L14: 2026-09-22
A15: Data Quality | B15: DQ-01 | C15: Inject controlled operational defects and build manifest | D15: Data Quality Engineer | E15: Complete | F15: High | G15: 2026-09-22 | H15: 2026-09-23 | I15: DAT-04 | J15: 100 | K15: Injected 44 realistic defects across 6 dimensions into raw layer | L15: 2026-09-23
A16: Data Quality | B16: DQ-02 | C16: Build automated data quality validation engine | D16: Data Quality Engineer | E16: Complete | F16: Critical | G16: 2026-09-23 | H16: 2026-09-24 | I16: DQ-01 | J16: 100 | K16: Codified rules DQ001 to DQ012 with 99.98% pass rate verification | L16: 2026-09-24
A17: Data Quality | B17: DQ-03 | C17: Build data cleaning and standardization pipeline | D17: Data Quality Engineer | E17: Complete | F17: Critical | G17: 2026-09-24 | H17: 2026-09-25 | I17: DQ-02 | J17: 100 | K17: Standardized geocoding and resolved all 44 manifest issues | L17: 2026-09-25
A18: Analytics | B18: ANA-01 | C18: Deploy relational DDL schema and load clean tables | D18: SQL Developer | E18: Complete | F18: High | G18: 2026-09-25 | H18: 2026-09-26 | I18: DQ-03 | J18: 100 | K18: Loaded 12 tables into relational DB with 0 FK violations | L18: 2026-09-26
A19: Analytics | B19: ANA-02 | C19: Develop analytical SQL query and views library | D19: SQL Developer | E19: Complete | F19: High | G19: 2026-09-26 | H19: 2026-09-27 | I19: ANA-01 | J19: 100 | K19: Implemented 16 business queries and 7 analytical reporting views | L19: 2026-09-27
A20: Analytics | B20: ANA-03 | C20: Execute exploratory analysis and render diagnostic charts | D20: BI Analyst | E20: Complete | F20: High | G20: 2026-09-27 | H20: 2026-09-28 | I20: ANA-02 | J20: 100 | K20: Generated 5 publication charts for weekday matrix cost and PAI | L20: 2026-09-28
A21: Analytics | B21: ANA-04 | C21: Compute Portfolio Attention Index and sensitivity analysis | D21: BI Analyst | E21: Complete | F21: Critical | G21: 2026-09-28 | H21: 2026-09-29 | I21: ANA-03 | J21: 100 | K21: Validated 5-factor PAI with Spearman rho > 0.97 across 4 schemes | L21: 2026-09-29
A22: Analytics | B22: ANA-05 | C22: Build capacity consolidation decision scenario model | D22: Lead Analyst | E22: Complete | F22: Medium | G22: 2026-09-29 | H22: 2026-09-30 | I22: ANA-04 | J22: 100 | K22: Modeled 10% 15% and 20% seat surrender scenarios with cost elasticity | L22: 2026-09-30
... A32: Documentation | B32: DOC-01 | C32: Perform humanization audit and finalize README portfolio | D32: Lead Analyst | E32: Complete | F32: Critical | G32: 2026-10-02 | H32: 2026-10-02 | I32: QA-03 | J32: 100 | K32: Removed generic AI buzzwords and finalized GitHub portfolio structure | L32: 2026-10-02

Sheet Methodology
A2: ANALYTICAL METHODOLOGY & METRIC FORMULARY
A3: Mathematical formulations, spatial definitions, and professional benchmark references
A5: 1. Spatial Area Measurement
A6: Usable Area (m²) represents net internal workable office floor space excluding building cores, lift lobbies, and vertical mechanical shafts. Rentable Area includes pro-rata common core areas. BOMA loss factor = (Rentable - Usable) / Rentable.
A8: 2. Workplace Utilization Formulation
A9: Average Utilization Rate % = Sum of Actual Occupied Hours divided by Available Capacity Hours (Capacity x 10 operating hours/day). Peak Utilization % = Maximum concurrent occupants observed during peak hour divided by capacity.
A11: 3. Capacity Pressure Choke Point
A12: Defined as the percentage of business days where peak utilization equals or exceeds 85.0%. Facilities operating above this threshold experience acute meeting room shortages and desk crowding.
A14: 4. Occupancy Cost Metrics
A15: Cost per Available Seat = Annual Operating Cost / Capacity Seats. Cost per Occupied Seat = Annual Operating Cost / Average Daily Presence. Utilization Cost Premium = Difference between occupied cost and available seat carrying cost.
A17: 5. Portfolio Attention Index (PAI)
A18: Project-defined prioritization score (0 to 100): 30% Utilization Inefficiency + 20% Cost Intensity + 20% Lease Exposure + 15% Capacity Pressure + 15% Data Quality Risk. Sensitivity testing confirms rank stability (Spearman rho > 0.97).
... A24: The operational dataset in this workbook is synthetic and generated programmatically for analytical demonstration. It does not represent any real organization's properties or lease liabilities.
